titulus/__init__.py
titulus/gradient_color.py
titulus-0.0.1.dist-info/LICENSE
titulus-0.0.1.dist-info/METADATA
titulus-0.0.1.dist-info/WHEEL
titulus-0.0.1.dist-info/top_level.txt
titulus-0.0.1.dist-info/RECORD
