Metadata-Version: 2.1
Name: titulus
Version: 0.0.1
Summary: Text visualization python package
Home-page: https://github.com/AntoineSimoulin/titulus
Author: Antoine Simoulin
Author-email: antoine.simoulin@gmail.com
License: UNKNOWN
Platform: UNKNOWN
Classifier: Programming Language :: Python :: 3
Classifier: License :: OSI Approved :: Apache Software License
Classifier: Operating System :: OS Independent
